[
    {
        "id": 1,
        "firstName": "Malek",
        "lastName": "Hizaoui",
        "phoneNumber": 21345350,
        "age": 23,
        "email": "",
        "reservation": [
            {
                "monday": [
                    {
                        "from": 17,
                        "to": 18,
                        "reservation": "pending"
                    }
                ],
                "tuesday": [
                    {
                        "from": 17,
                        "to": 18,
                        "reservation": "pending"
                    }
                ]
            }
        ]
    }
]